{
  "group_id": 2114564,
  "name": "Model 3",
  "runs": [
    {
      "id": 102882965,
      "group_id": 2114564,
      "name": "Heat 3",
      "type": "2",
      "started_at": "2024-08-17 22:00:00 UTC",
      "ended_at": "2024-08-17 22:14:54 UTC",
      "last_received_data_at": "2024-08-17 22:23:07 UTC",
      "status": "PROVISIONAL",
      "total_laps": 12,
      "has_results": true,
      "results_url": "https://api.racehero.io/events/gridlife-circuit-legends-2024/results/1073742028"
    },
    {
      "id": 102875195,
      "group_id": 2114564,
      "name": "Heat 2",
      "type": "2",
      "started_at": "2024-08-17 18:40:00 UTC",
      "ended_at": "2024-08-17 18:54:25 UTC",
      "last_received_data_at": "2024-08-17 18:58:54 UTC",
      "status": "PROVISIONAL",
      "total_laps": 11,
      "has_results": true,
      "results_url": "https://api.racehero.io/events/gridlife-circuit-legends-2024/results/1073742027"
    },
    {
      "id": 102859483,
      "group_id": 2114564,
      "name": "Heat 1",
      "type": "2",
      "started_at": "2024-08-17 12:40:00 UTC",
      "ended_at": "2024-08-17 12:54:44 UTC",
      "last_received_data_at": "2024-08-17 12:57:10 UTC",
      "status": "PROVISIONAL",
      "total_laps": 11,
      "has_results": true,
      "results_url": "https://api.racehero.io/events/gridlife-circuit-legends-2024/results/1073742026"
    },
    {
      "id": 102829691,
      "group_id": 2114564,
      "name": "Qualifying 1",
      "type": "1",
      "started_at": "2024-08-16 22:00:00 UTC",
      "ended_at": "2024-08-16 22:27:20 UTC",
      "last_received_data_at": "2024-08-16 22:19:40 UTC",
      "status": "PROVISIONAL",
      "total_laps": 20,
      "has_results": true,
      "results_url": "https://api.racehero.io/events/gridlife-circuit-legends-2024/results/1073742020"
    },
    {
      "id": 102818116,
      "group_id": 2114564,
      "name": "Practice 2",
      "type": "0",
      "started_at": "2024-08-16 16:35:00 UTC",
      "ended_at": "2024-08-16 16:47:29 UTC",
      "last_received_data_at": "2024-08-16 16:55:07 UTC",
      "status": "PROVISIONAL",
      "total_laps": 8,
      "has_results": true,
      "results_url": "https://api.racehero.io/events/gridlife-circuit-legends-2024/results/1073742019"
    },
    {
      "id": 102808600,
      "group_id": 2114564,
      "name": "Practice 1",
      "type": "0",
      "started_at": "2024-08-16 12:40:00 UTC",
      "ended_at": "2024-08-16 12:59:42 UTC",
      "last_received_data_at": "2024-08-16 12:59:52 UTC",
      "status": "PROVISIONAL",
      "total_laps": 15,
      "has_results": true,
      "results_url": "https://api.racehero.io/events/gridlife-circuit-legends-2024/results/1073742011"
    }
  ],
  "attributes_labels": {
    "attribute1": "Nat/State",
    "attribute2": "Sponsor",
    "attribute3": "Make",
    "attribute4": "Hometown",
    "attribute5": "Club",
    "attribute6": "Model/Engine",
    "attribute7": "Tires",
    "attribute8": "Email"
  },
  "racers": [
    {
      "name": "Jessie Tong",
      "number": "119",
      "class": "MODEL 3 - RWD",
      "attributes": {
        "attribute0": null,
        "attribute1": null,
        "attribute2": null,
        "attribute3": null,
        "attribute4": null,
        "attribute5": null,
        "attribute6": null,
        "attribute7": null,
        "attribute8": null
      }
    },
    {
      "name": "Phillippe Gelinas",
      "number": "348",
      "class": "MODEL 3 - AWD",
      "attributes": {
        "attribute0": null,
        "attribute1": null,
        "attribute2": null,
        "attribute3": null,
        "attribute4": null,
        "attribute5": null,
        "attribute6": null,
        "attribute7": null,
        "attribute8": null
      }
    },
    {
      "name": "Josh Hatch",
      "number": "152",
      "class": "MODEL 3 - RWD",
      "attributes": {
        "attribute0": null,
        "attribute1": null,
        "attribute2": null,
        "attribute3": null,
        "attribute4": null,
        "attribute5": null,
        "attribute6": null,
        "attribute7": null,
        "attribute8": null
      }
    },
    {
      "name": "Michael Rocha",
      "number": "905",
      "class": "MODEL 3 - AWD",
      "attributes": {
        "attribute0": null,
        "attribute1": null,
        "attribute2": null,
        "attribute3": null,
        "attribute4": null,
        "attribute5": null,
        "attribute6": null,
        "attribute7": null,
        "attribute8": null
      }
    },
    {
      "name": "Stephen Turney",
      "number": "341",
      "class": "MODEL 3 - AWD",
      "attributes": {
        "attribute0": null,
        "attribute1": null,
        "attribute2": null,
        "attribute3": null,
        "attribute4": null,
        "attribute5": null,
        "attribute6": null,
        "attribute7": null,
        "attribute8": null
      }
    },
    {
      "name": "David Schlessman",
      "number": "173",
      "class": "MODEL 3 - AWD",
      "attributes": {
        "attribute0": null,
        "attribute1": null,
        "attribute2": null,
        "attribute3": null,
        "attribute4": null,
        "attribute5": null,
        "attribute6": null,
        "attribute7": null,
        "attribute8": null
      }
    },
    {
      "name": "Bev Jones",
      "number": "366",
      "class": "",
      "attributes": {
        "attribute0": null,
        "attribute1": null,
        "attribute2": null,
        "attribute3": null,
        "attribute4": null,
        "attribute5": null,
        "attribute6": null,
        "attribute7": null,
        "attribute8": null
      }
    },
    {
      "name": "Alex Vongnhay",
      "number": "312",
      "class": "",
      "attributes": {
        "attribute0": null,
        "attribute1": null,
        "attribute2": null,
        "attribute3": null,
        "attribute4": null,
        "attribute5": null,
        "attribute6": null,
        "attribute7": null,
        "attribute8": null
      }
    },
    {
      "name": "Andrew Dekoning",
      "number": "232",
      "class": "MODEL 3 - AWD",
      "attributes": {
        "attribute0": null,
        "attribute1": null,
        "attribute2": null,
        "attribute3": null,
        "attribute4": null,
        "attribute5": null,
        "attribute6": null,
        "attribute7": null,
        "attribute8": null
      }
    },
    {
      "name": "Team Speed Academy",
      "number": "160",
      "class": "",
      "attributes": {
        "attribute0": null,
        "attribute1": null,
        "attribute2": null,
        "attribute3": null,
        "attribute4": null,
        "attribute5": null,
        "attribute6": null,
        "attribute7": null,
        "attribute8": null
      }
    },
    {
      "name": "Rudolph Xu",
      "number": "16",
      "class": "",
      "attributes": {
        "attribute0": null,
        "attribute1": null,
        "attribute2": null,
        "attribute3": null,
        "attribute4": null,
        "attribute5": null,
        "attribute6": null,
        "attribute7": null,
        "attribute8": null
      }
    }
  ]
}